ovos_microphone_plugin_files/__init__.py
ovos_microphone_plugin_files/version.py
ovos_microphone_plugin_files-0.0.1.dist-info/licenses/LICENSE
ovos_microphone_plugin_files-0.0.1.dist-info/METADATA
ovos_microphone_plugin_files-0.0.1.dist-info/WHEEL
ovos_microphone_plugin_files-0.0.1.dist-info/entry_points.txt
ovos_microphone_plugin_files-0.0.1.dist-info/top_level.txt
ovos_microphone_plugin_files-0.0.1.dist-info/zip-safe
ovos_microphone_plugin_files-0.0.1.dist-info/RECORD
